mydoro/__init__.py
mydoro/__main__.py
mydoro/app.css
mydoro/app.py
mydoro/main.py
mydoro/timer_state.py
mydoro/screen/__init__.py
mydoro/screen/getDuration.py
mydoro/screen/homescreen.py
mydoro/utils/__init__.py
mydoro/utils/config.py
mydoro/utils/timer_utils.py
mydoro/widgets/__init__.py
mydoro/widgets/digits.py
mydoro-1.0.0.dist-info/licenses/LICENSE
mydoro-1.0.0.dist-info/METADATA
mydoro-1.0.0.dist-info/WHEEL
mydoro-1.0.0.dist-info/entry_points.txt
mydoro-1.0.0.dist-info/top_level.txt
mydoro-1.0.0.dist-info/RECORD
