Metadata-Version: 2.4
Name: mydoro
Version: 1.0.0
Summary: ✨ MyDoro: A sleek, modern Pomodoro timer for your terminal. Boost productivity with customizable work/break intervals, beautiful themes, and a distraction-free CLI experience. Perfect for developers who value both functionality and aesthetics.
Author-email: Balaji <j.balaji2468@gmail.com>
License-Expression: MIT
Classifier: Programming Language :: Python :: 3
Classifier: Operating System :: OS Independent
Classifier: Environment :: Console
Classifier: Topic :: Utilities
Requires-Python: >=3.10
License-File: LICENSE
Requires-Dist: linkify-it-py>=2.0.3
Requires-Dist: markdown-it-py>=3.0.0
Requires-Dist: mdit-py-plugins>=0.4.2
Requires-Dist: mdurl>=0.1.2
Requires-Dist: platformdirs>=4.3.8
Requires-Dist: pygments>=2.19.1
Requires-Dist: rich>=14.0.0
Requires-Dist: textual>=3.3.0
Requires-Dist: typing-extensions>=4.14.0
Requires-Dist: uc-micro-py>=1.0.3
Requires-Dist: plyer>=2.1.0
Dynamic: license-file
